LICENSE
README.md
setup.py
divtel/__init__.py
divtel/pointing.py
divtel/telescope.py
divtel/version.py
divtel/visualization.py
divtel.egg-info/PKG-INFO
divtel.egg-info/SOURCES.txt
divtel.egg-info/dependency_links.txt
divtel.egg-info/requires.txt
divtel.egg-info/top_level.txt