Metadata-Version: 2.1
Name: divtel
Version: 0.1
Summary: Divergent pointing mode for Imaging Atmospheric Cherenkov Telescopes arrays
Home-page: https://github.com/cta-observatory/divtel
Author: T. Vuillaume, A. Donini, T. Gasparetto
Author-email: thomas.vuillaume@lapp.in2p3.fr
License: MIT
Platform: UNKNOWN
Provides-Extra: tests
Provides-Extra: examples
License-File: LICENSE
